ue_uploader/__init__.py
ue_uploader/__main__.py
ue_uploader/library_up.py
ue_uploader/uploader.py
ue_uploader-0.0.2.dist-info/LICENSE
ue_uploader-0.0.2.dist-info/METADATA
ue_uploader-0.0.2.dist-info/WHEEL
ue_uploader-0.0.2.dist-info/top_level.txt
ue_uploader-0.0.2.dist-info/RECORD
