Metadata-Version: 2.1
Name: ue-uploader
Version: 0.0.2
Summary: Uploader tool for flashing firmware onto the CH552 device. v0.0.2
Author: Master
Author-email: name@email.com
License: GPL-3.0 License
License-File: LICENSE
Requires-Dist: tk
